stinger_ipc-0.6.5.dist-info/licenses/LICENSE
stingeripc/__init__.py
stingeripc/args.py
stingeripc/asyncapi.py
stingeripc/components.py
stingeripc/config.py
stingeripc/connection.py
stingeripc/exceptions.py
stingeripc/filtering.py
stingeripc/interface.py
stingeripc/lang_symb.py
stingeripc/models.py
stingeripc/topic.py
stingeripc/schema/schema.yaml
stingeripc/symbols/__init__.py
stingeripc/symbols/protobuf.py
stingeripc/templates/cpp/CMakeLists.txt.jinja2
stingeripc/templates/cpp/cmake/config.cmake.in.jinja2
stingeripc/templates/cpp/examples/client_main.cpp.jinja2
stingeripc/templates/cpp/examples/discovery_example.cpp.jinja2
stingeripc/templates/cpp/examples/discovery_publisher.cpp.jinja2
stingeripc/templates/cpp/examples/server_main.cpp.jinja2
stingeripc/templates/cpp/include/broker.hpp.jinja2
stingeripc/templates/cpp/include/client.hpp.jinja2
stingeripc/templates/cpp/include/conversions.hpp.jinja2
stingeripc/templates/cpp/include/discovery.hpp.jinja2
stingeripc/templates/cpp/include/enums.hpp.jinja2
stingeripc/templates/cpp/include/ibrokerconnection.hpp.jinja2
stingeripc/templates/cpp/include/interface_exceptions.hpp.jinja2
stingeripc/templates/cpp/include/method_payloads.hpp.jinja2
stingeripc/templates/cpp/include/property_structs.hpp.jinja2
stingeripc/templates/cpp/include/server.hpp.jinja2
stingeripc/templates/cpp/include/signal_payloads.hpp.jinja2
stingeripc/templates/cpp/include/structs.hpp.jinja2
stingeripc/templates/cpp/include/utils.hpp.jinja2
stingeripc/templates/cpp/partials/args.jinja2
stingeripc/templates/cpp/partials/deserialize.jinja2
stingeripc/templates/cpp/partials/properties.jinja2
stingeripc/templates/cpp/partials/serialize.jinja2
stingeripc/templates/cpp/src/broker.cpp.jinja2
stingeripc/templates/cpp/src/client.cpp.jinja2
stingeripc/templates/cpp/src/conversions.cpp.jinja2
stingeripc/templates/cpp/src/discovery.cpp.jinja2
stingeripc/templates/cpp/src/interface_exceptions.cpp.jinja2
stingeripc/templates/cpp/src/method_payloads.cpp.jinja2
stinger_ipc-0.6.5.dist-info/METADATA
stinger_ipc-0.6.5.dist-info/WHEEL
stinger_ipc-0.6.5.dist-info/entry_points.txt
stinger_ipc-0.6.5.dist-info/top_level.txt
stinger_ipc-0.6.5.dist-info/RECORD
