Metadata-Version: 2.4
Name: stinger-ipc
Version: 0.6.5
Summary: Tools to create code to do IPC over MQTT
License: MIT License
Classifier: License :: OSI Approved :: MIT License
Requires-Python: >=3.12
License-File: LICENSE
Requires-Dist: go-task-bin>=3.46.2
Requires-Dist: jacobs-jinja-too>=0.2.10
Requires-Dist: jsonschema-rs>=0.34.0
Requires-Dist: packaging>=25.0
Requires-Dist: pydantic>=2.11.7
Requires-Dist: pydantic-asyncapi>=0.3.0
Requires-Dist: pyyaml>=6.0.2
Requires-Dist: ruamel-yaml>=0.18.14
Requires-Dist: semantic-version>=2.10.0
Requires-Dist: stevedore>=5.5.0
Requires-Dist: typer>=0.16.1
Requires-Dist: yamlloader>=1.5.1
Dynamic: license-file
